tokencostauto/__init__.py
tokencostauto/constants.py
tokencostauto/costs.py
tokencostauto/model_prices.json
tokencostauto-0.1.480.dist-info/licenses/LICENSE
tokencostauto-0.1.480.dist-info/METADATA
tokencostauto-0.1.480.dist-info/WHEEL
tokencostauto-0.1.480.dist-info/top_level.txt
tokencostauto-0.1.480.dist-info/RECORD
