Metadata-Version: 2.4
Name: tokencostauto
Version: 0.1.480
Summary: To calculate token and translated USD cost of string and message calls to OpenAI, for example when used by AI agents
Author-email: Trisha Pan <trishaepan@gmail.com>, Alex Reibman <areibman@gmail.com>, Pratyush Shukla <ps4534@nyu.edu>, Thiago MadPin <madpin@gmail.com>
Project-URL: Homepage, https://github.com/madpin/tokencostaudo
Project-URL: Issues, https://github.com/madpin/tokencostauto/issues
Classifier: Programming Language :: Python :: 3
Classifier: License :: OSI Approved :: MIT License
Classifier: Operating System :: OS Independent
Requires-Python: >=3.9
License-File: LICENSE
Requires-Dist: tiktoken>=0.9.0
Requires-Dist: aiohttp>=3.9.3
Requires-Dist: anthropic>=0.34.0
Provides-Extra: dev
Requires-Dist: pytest>=7.4.4; extra == "dev"
Requires-Dist: flake8>=3.1.0; extra == "dev"
Requires-Dist: coverage[toml]>=7.4.0; extra == "dev"
Requires-Dist: tach>=0.6.9; extra == "dev"
Requires-Dist: tabulate>=0.9.0; extra == "dev"
Requires-Dist: pandas>=2.1.0; extra == "dev"
Dynamic: license-file
